setup.cfg
setup.py
bin/opendig
namecoinrpc/__init__.py
namecoinrpc/config.py
namecoinrpc/connection.py
namecoinrpc/data.py
namecoinrpc/exceptions.py
namecoinrpc/proxy.py
namecoinrpc/util.py
opendig/__init__.py
opendig/config_default.py
opendig/dns_resolver.py
opendig/ons_resolver.py
opendig.egg-info/PKG-INFO
opendig.egg-info/SOURCES.txt
opendig.egg-info/dependency_links.txt
opendig.egg-info/not-zip-safe
opendig.egg-info/requires.txt
opendig.egg-info/top_level.txt