Metadata-Version: 1.1
Name: opendig
Version: 0.1.0
Summary: A command-line tool for the Open Name System (the equivalent of dig for DNS).
Home-page: https://github.com/opennamesystem/opendig
Author: Muneeb Ali (@muneeb), Ryan Shea (@ryaneshea)
Author-email: hello@halfmoonlabs.com
License: MIT
Download-URL: https://github.com/opennamesystem/opendig/archive/master.zip
Keywords: domain,name,resolution,bitcoin,address
Platform: UNKNOWN
Classifier: Intended Audience :: Developers
Classifier: License :: OSI Approved :: MIT License
Classifier: Operating System :: OS Independent
Classifier: Programming Language :: Python
